[
    {
        "type": "message",
        "text": "Hello, This is my profile picture screenshot",
        "files": [
            {
                "id": "F04M6APDWLT",
                "created": 1675104560,
                "timestamp": 1675104560,
                "name": "Screen Shot 2023-01-30 at 12.44.28 PM.png",
                "title": "Screen Shot 2023-01-30 at 12.44.28 PM.png",
                "mimetype": "image\/png",
                "filetype": "png",
                "pretty_type": "PNG",
                "user": "U04L1QX8HN0",
                "user_team": "T04HC2CMNJ0",
                "editable": false,
                "size": 342276,
                "mode": "hosted",
                "is_external": false,
                "external_type": "",
                "is_public": true,
                "public_url_shared": false,
                "display_as_bot": false,
                "username": "",
                "url_private": "https:\/\/files.slack.com\/files-pri\/T04HC2CMNJ0-F04M6APDWLT\/screen_shot_2023-01-30_at_12.44.28_pm.png?t=xoxe-4590080736612-5103277303719-5114876852661-7c6954f20f96cb848404111e9d27c8e9",
                "url_private_download": "https:\/\/files.slack.com\/files-pri\/T04HC2CMNJ0-F04M6APDWLT\/download\/screen_shot_2023-01-30_at_12.44.28_pm.png?t=xoxe-4590080736612-5103277303719-5114876852661-7c6954f20f96cb848404111e9d27c8e9",
                "media_display_type": "unknown",
                "thumb_64": "https:\/\/files.slack.com\/files-tmb\/T04HC2CMNJ0-F04M6APDWLT-6ee614b6bb\/screen_shot_2023-01-30_at_12.44.28_pm_64.png?t=xoxe-4590080736612-5103277303719-5114876852661-7c6954f20f96cb848404111e9d27c8e9",
                "thumb_80": "https:\/\/files.slack.com\/files-tmb\/T04HC2CMNJ0-F04M6APDWLT-6ee614b6bb\/screen_shot_2023-01-30_at_12.44.28_pm_80.png?t=xoxe-4590080736612-5103277303719-5114876852661-7c6954f20f96cb848404111e9d27c8e9",
                "thumb_360": "https:\/\/files.slack.com\/files-tmb\/T04HC2CMNJ0-F04M6APDWLT-6ee614b6bb\/screen_shot_2023-01-30_at_12.44.28_pm_360.png?t=xoxe-4590080736612-5103277303719-5114876852661-7c6954f20f96cb848404111e9d27c8e9",
                "thumb_360_w": 281,
                "thumb_360_h": 360,
                "thumb_480": "https:\/\/files.slack.com\/files-tmb\/T04HC2CMNJ0-F04M6APDWLT-6ee614b6bb\/screen_shot_2023-01-30_at_12.44.28_pm_480.png?t=xoxe-4590080736612-5103277303719-5114876852661-7c6954f20f96cb848404111e9d27c8e9",
                "thumb_480_w": 375,
                "thumb_480_h": 480,
                "thumb_160": "https:\/\/files.slack.com\/files-tmb\/T04HC2CMNJ0-F04M6APDWLT-6ee614b6bb\/screen_shot_2023-01-30_at_12.44.28_pm_160.png?t=xoxe-4590080736612-5103277303719-5114876852661-7c6954f20f96cb848404111e9d27c8e9",
                "thumb_720": "https:\/\/files.slack.com\/files-tmb\/T04HC2CMNJ0-F04M6APDWLT-6ee614b6bb\/screen_shot_2023-01-30_at_12.44.28_pm_720.png?t=xoxe-4590080736612-5103277303719-5114876852661-7c6954f20f96cb848404111e9d27c8e9",
                "thumb_720_w": 563,
                "thumb_720_h": 720,
                "thumb_800": "https:\/\/files.slack.com\/files-tmb\/T04HC2CMNJ0-F04M6APDWLT-6ee614b6bb\/screen_shot_2023-01-30_at_12.44.28_pm_800.png?t=xoxe-4590080736612-5103277303719-5114876852661-7c6954f20f96cb848404111e9d27c8e9",
                "thumb_800_w": 625,
                "thumb_800_h": 800,
                "image_exif_rotation": 1,
                "original_w": 688,
                "original_h": 880,
                "thumb_tiny": "AwAwACWpboJJ1Q9CasvbIp+7+tQWfF1H9f6VfncLGWIzSY0UWWMPt70jRqFJx0FM87Mm5h+VTt\/q2+lLUZVpaSlqiSW1\/wCPlPr\/AEq3d48hie3SqURKMrqy5HYmpZJ3kTBKAdeKTQytEu+TGM1ckGEb6VWjkMZyAM+9OadmBBA5osBFS0UlMQo+o\/OjNAPvilJ9GzQA2il6nk0UAJS0lFAH\/9k=",
                "permalink": "https:\/\/is-1003-spring-2023.slack.com\/files\/U04L1QX8HN0\/F04M6APDWLT\/screen_shot_2023-01-30_at_12.44.28_pm.png",
                "permalink_public": "https:\/\/slack-files.com\/T04HC2CMNJ0-F04M6APDWLT-15dd397426",
                "is_starred": false,
                "has_rich_preview": false,
                "file_access": "visible"
            }
        ],
        "upload": false,
        "user": "U04L1QX8HN0",
        "display_as_bot": false,
        "ts": "1675104585.567359",
        "blocks": [
            {
                "type": "rich_text",
                "block_id": "MH7K",
                "elements": [
                    {
                        "type": "rich_text_section",
                        "elements": [
                            {
                                "type": "text",
                                "text": "Hello, This is my profile picture screenshot"
                            }
                        ]
                    }
                ]
            }
        ],
        "client_msg_id": "4f753929-faa2-4a7d-a198-b25701be1dc7"
    },
    {
        "type": "message",
        "text": "",
        "files": [
            {
                "id": "F04M023NB1C",
                "created": 1675106413,
                "timestamp": 1675106413,
                "name": "D0D60EA1-093D-42DA-89FD-D3A8EA9B5F67_1_201_a.jpeg",
                "title": "D0D60EA1-093D-42DA-89FD-D3A8EA9B5F67_1_201_a.jpeg",
                "mimetype": "image\/jpeg",
                "filetype": "jpg",
                "pretty_type": "JPEG",
                "user": "U04M92TC78C",
                "user_team": "T04HC2CMNJ0",
                "editable": false,
                "size": 43320,
                "mode": "hosted",
                "is_external": false,
                "external_type": "",
                "is_public": true,
                "public_url_shared": false,
                "display_as_bot": false,
                "username": "",
                "url_private": "https:\/\/files.slack.com\/files-pri\/T04HC2CMNJ0-F04M023NB1C\/d0d60ea1-093d-42da-89fd-d3a8ea9b5f67_1_201_a.jpeg?t=xoxe-4590080736612-5103277303719-5114876852661-7c6954f20f96cb848404111e9d27c8e9",
                "url_private_download": "https:\/\/files.slack.com\/files-pri\/T04HC2CMNJ0-F04M023NB1C\/download\/d0d60ea1-093d-42da-89fd-d3a8ea9b5f67_1_201_a.jpeg?t=xoxe-4590080736612-5103277303719-5114876852661-7c6954f20f96cb848404111e9d27c8e9",
                "media_display_type": "unknown",
                "thumb_64": "https:\/\/files.slack.com\/files-tmb\/T04HC2CMNJ0-F04M023NB1C-90c60d6fdc\/d0d60ea1-093d-42da-89fd-d3a8ea9b5f67_1_201_a_64.jpg?t=xoxe-4590080736612-5103277303719-5114876852661-7c6954f20f96cb848404111e9d27c8e9",
                "thumb_80": "https:\/\/files.slack.com\/files-tmb\/T04HC2CMNJ0-F04M023NB1C-90c60d6fdc\/d0d60ea1-093d-42da-89fd-d3a8ea9b5f67_1_201_a_80.jpg?t=xoxe-4590080736612-5103277303719-5114876852661-7c6954f20f96cb848404111e9d27c8e9",
                "thumb_360": "https:\/\/files.slack.com\/files-tmb\/T04HC2CMNJ0-F04M023NB1C-90c60d6fdc\/d0d60ea1-093d-42da-89fd-d3a8ea9b5f67_1_201_a_360.jpg?t=xoxe-4590080736612-5103277303719-5114876852661-7c6954f20f96cb848404111e9d27c8e9",
                "thumb_360_w": 360,
                "thumb_360_h": 311,
                "thumb_480": "https:\/\/files.slack.com\/files-tmb\/T04HC2CMNJ0-F04M023NB1C-90c60d6fdc\/d0d60ea1-093d-42da-89fd-d3a8ea9b5f67_1_201_a_480.jpg?t=xoxe-4590080736612-5103277303719-5114876852661-7c6954f20f96cb848404111e9d27c8e9",
                "thumb_480_w": 480,
                "thumb_480_h": 414,
                "thumb_160": "https:\/\/files.slack.com\/files-tmb\/T04HC2CMNJ0-F04M023NB1C-90c60d6fdc\/d0d60ea1-093d-42da-89fd-d3a8ea9b5f67_1_201_a_160.jpg?t=xoxe-4590080736612-5103277303719-5114876852661-7c6954f20f96cb848404111e9d27c8e9",
                "thumb_720": "https:\/\/files.slack.com\/files-tmb\/T04HC2CMNJ0-F04M023NB1C-90c60d6fdc\/d0d60ea1-093d-42da-89fd-d3a8ea9b5f67_1_201_a_720.jpg?t=xoxe-4590080736612-5103277303719-5114876852661-7c6954f20f96cb848404111e9d27c8e9",
                "thumb_720_w": 720,
                "thumb_720_h": 621,
                "thumb_800": "https:\/\/files.slack.com\/files-tmb\/T04HC2CMNJ0-F04M023NB1C-90c60d6fdc\/d0d60ea1-093d-42da-89fd-d3a8ea9b5f67_1_201_a_800.jpg?t=xoxe-4590080736612-5103277303719-5114876852661-7c6954f20f96cb848404111e9d27c8e9",
                "thumb_800_w": 800,
                "thumb_800_h": 690,
                "original_w": 840,
                "original_h": 725,
                "thumb_tiny": "AwApADCgTn0ooooAlii8xSd2OfSn\/Zv9v9KW2\/1Z+tWZCCeDxUNu5tGKaRnuuxyuc4ptPm\/1rfWmVa2MnuOwvvTaXt\/9ak4oEPSRkGFP6Uvnyeo\/Ko6KLIfMxWYsxJ6mkoooEOzx\/wDXptFFABRRRQAUUUUAf\/\/Z",
                "permalink": "https:\/\/is-1003-spring-2023.slack.com\/files\/U04M92TC78C\/F04M023NB1C\/d0d60ea1-093d-42da-89fd-d3a8ea9b5f67_1_201_a.jpeg",
                "permalink_public": "https:\/\/slack-files.com\/T04HC2CMNJ0-F04M023NB1C-8e72e156d7",
                "is_starred": false,
                "has_rich_preview": false,
                "file_access": "visible"
            }
        ],
        "upload": false,
        "user": "U04M92TC78C",
        "display_as_bot": false,
        "ts": "1675106417.899889",
        "client_msg_id": "433bfc5f-814a-4384-9548-dddd4eb9bf29"
    },
    {
        "type": "message",
        "text": "Hello everyone, this is my profile",
        "files": [
            {
                "id": "F04MWAHMYQG",
                "created": 1675106361,
                "timestamp": 1675106361,
                "name": "Lab00.png",
                "title": "Lab00.png",
                "mimetype": "image\/png",
                "filetype": "png",
                "pretty_type": "PNG",
                "user": "U04LE2A99QE",
                "user_team": "T04HC2CMNJ0",
                "editable": false,
                "size": 287012,
                "mode": "hosted",
                "is_external": false,
                "external_type": "",
                "is_public": true,
                "public_url_shared": false,
                "display_as_bot": false,
                "username": "",
                "url_private": "https:\/\/files.slack.com\/files-pri\/T04HC2CMNJ0-F04MWAHMYQG\/lab00.png?t=xoxe-4590080736612-5103277303719-5114876852661-7c6954f20f96cb848404111e9d27c8e9",
                "url_private_download": "https:\/\/files.slack.com\/files-pri\/T04HC2CMNJ0-F04MWAHMYQG\/download\/lab00.png?t=xoxe-4590080736612-5103277303719-5114876852661-7c6954f20f96cb848404111e9d27c8e9",
                "media_display_type": "unknown",
                "thumb_64": "https:\/\/files.slack.com\/files-tmb\/T04HC2CMNJ0-F04MWAHMYQG-058830e2f4\/lab00_64.png?t=xoxe-4590080736612-5103277303719-5114876852661-7c6954f20f96cb848404111e9d27c8e9",
                "thumb_80": "https:\/\/files.slack.com\/files-tmb\/T04HC2CMNJ0-F04MWAHMYQG-058830e2f4\/lab00_80.png?t=xoxe-4590080736612-5103277303719-5114876852661-7c6954f20f96cb848404111e9d27c8e9",
                "thumb_360": "https:\/\/files.slack.com\/files-tmb\/T04HC2CMNJ0-F04MWAHMYQG-058830e2f4\/lab00_360.png?t=xoxe-4590080736612-5103277303719-5114876852661-7c6954f20f96cb848404111e9d27c8e9",
                "thumb_360_w": 247,
                "thumb_360_h": 360,
                "thumb_480": "https:\/\/files.slack.com\/files-tmb\/T04HC2CMNJ0-F04MWAHMYQG-058830e2f4\/lab00_480.png?t=xoxe-4590080736612-5103277303719-5114876852661-7c6954f20f96cb848404111e9d27c8e9",
                "thumb_480_w": 329,
                "thumb_480_h": 480,
                "thumb_160": "https:\/\/files.slack.com\/files-tmb\/T04HC2CMNJ0-F04MWAHMYQG-058830e2f4\/lab00_160.png?t=xoxe-4590080736612-5103277303719-5114876852661-7c6954f20f96cb848404111e9d27c8e9",
                "thumb_720": "https:\/\/files.slack.com\/files-tmb\/T04HC2CMNJ0-F04MWAHMYQG-058830e2f4\/lab00_720.png?t=xoxe-4590080736612-5103277303719-5114876852661-7c6954f20f96cb848404111e9d27c8e9",
                "thumb_720_w": 493,
                "thumb_720_h": 720,
                "thumb_800": "https:\/\/files.slack.com\/files-tmb\/T04HC2CMNJ0-F04MWAHMYQG-058830e2f4\/lab00_800.png?t=xoxe-4590080736612-5103277303719-5114876852661-7c6954f20f96cb848404111e9d27c8e9",
                "thumb_800_w": 548,
                "thumb_800_h": 800,
                "original_w": 577,
                "original_h": 842,
                "thumb_tiny": "AwAwACCmil\/lVQTjrSiCQ9F\/Wn2ePP5OODTyPnPXJbHFAEX2aX+7+tMdGjbDDBq+8LxrkMTVKckyZPpQA1MbxnpVryvKEbbjlhuz2qrs3Dqv51PPM02wDagQY4ekxphJcyA4Dkr\/ALQqGQsxBcAEgH8KesxRSpAYkdc1EWLYJ7AChAxQDSc9xQD60E+mfzqhCUUvGOnNJSA\/\/9k=",
                "permalink": "https:\/\/is-1003-spring-2023.slack.com\/files\/U04LE2A99QE\/F04MWAHMYQG\/lab00.png",
                "permalink_public": "https:\/\/slack-files.com\/T04HC2CMNJ0-F04MWAHMYQG-814c2ec5a9",
                "is_starred": false,
                "has_rich_preview": false,
                "file_access": "visible"
            }
        ],
        "upload": false,
        "user": "U04LE2A99QE",
        "display_as_bot": false,
        "ts": "1675106492.903369",
        "blocks": [
            {
                "type": "rich_text",
                "block_id": "2EVid",
                "elements": [
                    {
                        "type": "rich_text_section",
                        "elements": [
                            {
                                "type": "text",
                                "text": "Hello everyone, this is my profile"
                            }
                        ]
                    }
                ]
            }
        ],
        "client_msg_id": "1a55efa5-a274-49cb-a520-5ef2342e16e5"
    },
    {
        "client_msg_id": "4daff241-e1ee-481a-a3b5-dad41fd46451",
        "type": "message",
        "text": "<@U04KZMSE24X> Thank you!",
        "user": "U04LY71MCQ2",
        "ts": "1675107357.846449",
        "blocks": [
            {
                "type": "rich_text",
                "block_id": "ZZt",
                "elements": [
                    {
                        "type": "rich_text_section",
                        "elements": [
                            {
                                "type": "user",
                                "user_id": "U04KZMSE24X"
                            },
                            {
                                "type": "text",
                                "text": " Thank you!"
                            }
                        ]
                    }
                ]
            }
        ],
        "team": "T04HC2CMNJ0",
        "user_team": "T04HC2CMNJ0",
        "source_team": "T04HC2CMNJ0",
        "user_profile": {
            "avatar_hash": "8488b99f6ee7",
            "image_72": "https:\/\/avatars.slack-edge.com\/2023-01-27\/4712142459091_8488b99f6ee778a06893_72.jpg",
            "first_name": "Samantha",
            "real_name": "Samantha Bray",
            "display_name": "Samantha Bray",
            "team": "T04HC2CMNJ0",
            "name": "samantha.bray",
            "is_restricted": false,
            "is_ultra_restricted": false
        },
        "thread_ts": "1674861354.604409",
        "parent_user_id": "U04LY71MCQ2"
    },
    {
        "type": "message",
        "text": "Hello, This is my profile picture screenshot",
        "files": [
            {
                "id": "F04M6V37BAN",
                "created": 1675109616,
                "timestamp": 1675109616,
                "name": "module0.png",
                "title": "module0.png",
                "mimetype": "image\/png",
                "filetype": "png",
                "pretty_type": "PNG",
                "user": "U04KUH3E094",
                "user_team": "T04HC2CMNJ0",
                "editable": false,
                "size": 37983,
                "mode": "hosted",
                "is_external": false,
                "external_type": "",
                "is_public": true,
                "public_url_shared": false,
                "display_as_bot": false,
                "username": "",
                "url_private": "https:\/\/files.slack.com\/files-pri\/T04HC2CMNJ0-F04M6V37BAN\/module0.png?t=xoxe-4590080736612-5103277303719-5114876852661-7c6954f20f96cb848404111e9d27c8e9",
                "url_private_download": "https:\/\/files.slack.com\/files-pri\/T04HC2CMNJ0-F04M6V37BAN\/download\/module0.png?t=xoxe-4590080736612-5103277303719-5114876852661-7c6954f20f96cb848404111e9d27c8e9",
                "media_display_type": "unknown",
                "thumb_64": "https:\/\/files.slack.com\/files-tmb\/T04HC2CMNJ0-F04M6V37BAN-5a68e08635\/module0_64.png?t=xoxe-4590080736612-5103277303719-5114876852661-7c6954f20f96cb848404111e9d27c8e9",
                "thumb_80": "https:\/\/files.slack.com\/files-tmb\/T04HC2CMNJ0-F04M6V37BAN-5a68e08635\/module0_80.png?t=xoxe-4590080736612-5103277303719-5114876852661-7c6954f20f96cb848404111e9d27c8e9",
                "thumb_360": "https:\/\/files.slack.com\/files-tmb\/T04HC2CMNJ0-F04M6V37BAN-5a68e08635\/module0_360.png?t=xoxe-4590080736612-5103277303719-5114876852661-7c6954f20f96cb848404111e9d27c8e9",
                "thumb_360_w": 360,
                "thumb_360_h": 297,
                "thumb_480": "https:\/\/files.slack.com\/files-tmb\/T04HC2CMNJ0-F04M6V37BAN-5a68e08635\/module0_480.png?t=xoxe-4590080736612-5103277303719-5114876852661-7c6954f20f96cb848404111e9d27c8e9",
                "thumb_480_w": 480,
                "thumb_480_h": 395,
                "thumb_160": "https:\/\/files.slack.com\/files-tmb\/T04HC2CMNJ0-F04M6V37BAN-5a68e08635\/module0_160.png?t=xoxe-4590080736612-5103277303719-5114876852661-7c6954f20f96cb848404111e9d27c8e9",
                "thumb_720": "https:\/\/files.slack.com\/files-tmb\/T04HC2CMNJ0-F04M6V37BAN-5a68e08635\/module0_720.png?t=xoxe-4590080736612-5103277303719-5114876852661-7c6954f20f96cb848404111e9d27c8e9",
                "thumb_720_w": 720,
                "thumb_720_h": 593,
                "thumb_800": "https:\/\/files.slack.com\/files-tmb\/T04HC2CMNJ0-F04M6V37BAN-5a68e08635\/module0_800.png?t=xoxe-4590080736612-5103277303719-5114876852661-7c6954f20f96cb848404111e9d27c8e9",
                "thumb_800_w": 800,
                "thumb_800_h": 659,
                "thumb_960": "https:\/\/files.slack.com\/files-tmb\/T04HC2CMNJ0-F04M6V37BAN-5a68e08635\/module0_960.png?t=xoxe-4590080736612-5103277303719-5114876852661-7c6954f20f96cb848404111e9d27c8e9",
                "thumb_960_w": 960,
                "thumb_960_h": 791,
                "original_w": 994,
                "original_h": 819,
                "thumb_tiny": "AwAnADDTAA6UUZHrRQBXaSUzmNNvHqKFlkE4jfbz6CnCEmZpNxHPGKPJImWTcT65qtCLMmoooqSxuBnoKcMDgU3nPWnUAFFFFABRRRQAmRS5FNooAdkUZFNooAdkUZFNooA\/\/9k=",
                "permalink": "https:\/\/is-1003-spring-2023.slack.com\/files\/U04KUH3E094\/F04M6V37BAN\/module0.png",
                "permalink_public": "https:\/\/slack-files.com\/T04HC2CMNJ0-F04M6V37BAN-5d543d0895",
                "is_starred": false,
                "has_rich_preview": false,
                "file_access": "visible"
            }
        ],
        "upload": false,
        "user": "U04KUH3E094",
        "display_as_bot": false,
        "ts": "1675109647.572569",
        "blocks": [
            {
                "type": "rich_text",
                "block_id": "FzZF",
                "elements": [
                    {
                        "type": "rich_text_section",
                        "elements": [
                            {
                                "type": "text",
                                "text": "Hello, This is my profile picture screenshot"
                            }
                        ]
                    }
                ]
            }
        ],
        "client_msg_id": "ca3eda03-4b83-4ef6-a6eb-e2f71e1d8364"
    },
    {
        "type": "message",
        "text": "Hello everyone, this is my profile",
        "files": [
            {
                "id": "F04LSE53P0F",
                "created": 1675109944,
                "timestamp": 1675109944,
                "name": "Screenshot 2023-01-30 at 11.47.14 AM.png",
                "title": "Screenshot 2023-01-30 at 11.47.14 AM.png",
                "mimetype": "image\/png",
                "filetype": "png",
                "pretty_type": "PNG",
                "user": "U04LRCJ5LRM",
                "user_team": "T04HC2CMNJ0",
                "editable": false,
                "size": 123709,
                "mode": "hosted",
                "is_external": false,
                "external_type": "",
                "is_public": true,
                "public_url_shared": false,
                "display_as_bot": false,
                "username": "",
                "url_private": "https:\/\/files.slack.com\/files-pri\/T04HC2CMNJ0-F04LSE53P0F\/screenshot_2023-01-30_at_11.47.14_am.png?t=xoxe-4590080736612-5103277303719-5114876852661-7c6954f20f96cb848404111e9d27c8e9",
                "url_private_download": "https:\/\/files.slack.com\/files-pri\/T04HC2CMNJ0-F04LSE53P0F\/download\/screenshot_2023-01-30_at_11.47.14_am.png?t=xoxe-4590080736612-5103277303719-5114876852661-7c6954f20f96cb848404111e9d27c8e9",
                "media_display_type": "unknown",
                "thumb_64": "https:\/\/files.slack.com\/files-tmb\/T04HC2CMNJ0-F04LSE53P0F-7385412c1b\/screenshot_2023-01-30_at_11.47.14_am_64.png?t=xoxe-4590080736612-5103277303719-5114876852661-7c6954f20f96cb848404111e9d27c8e9",
                "thumb_80": "https:\/\/files.slack.com\/files-tmb\/T04HC2CMNJ0-F04LSE53P0F-7385412c1b\/screenshot_2023-01-30_at_11.47.14_am_80.png?t=xoxe-4590080736612-5103277303719-5114876852661-7c6954f20f96cb848404111e9d27c8e9",
                "thumb_360": "https:\/\/files.slack.com\/files-tmb\/T04HC2CMNJ0-F04LSE53P0F-7385412c1b\/screenshot_2023-01-30_at_11.47.14_am_360.png?t=xoxe-4590080736612-5103277303719-5114876852661-7c6954f20f96cb848404111e9d27c8e9",
                "thumb_360_w": 185,
                "thumb_360_h": 360,
                "thumb_480": "https:\/\/files.slack.com\/files-tmb\/T04HC2CMNJ0-F04LSE53P0F-7385412c1b\/screenshot_2023-01-30_at_11.47.14_am_480.png?t=xoxe-4590080736612-5103277303719-5114876852661-7c6954f20f96cb848404111e9d27c8e9",
                "thumb_480_w": 247,
                "thumb_480_h": 480,
                "thumb_160": "https:\/\/files.slack.com\/files-tmb\/T04HC2CMNJ0-F04LSE53P0F-7385412c1b\/screenshot_2023-01-30_at_11.47.14_am_160.png?t=xoxe-4590080736612-5103277303719-5114876852661-7c6954f20f96cb848404111e9d27c8e9",
                "thumb_720": "https:\/\/files.slack.com\/files-tmb\/T04HC2CMNJ0-F04LSE53P0F-7385412c1b\/screenshot_2023-01-30_at_11.47.14_am_720.png?t=xoxe-4590080736612-5103277303719-5114876852661-7c6954f20f96cb848404111e9d27c8e9",
                "thumb_720_w": 371,
                "thumb_720_h": 720,
                "thumb_800": "https:\/\/files.slack.com\/files-tmb\/T04HC2CMNJ0-F04LSE53P0F-7385412c1b\/screenshot_2023-01-30_at_11.47.14_am_800.png?t=xoxe-4590080736612-5103277303719-5114876852661-7c6954f20f96cb848404111e9d27c8e9",
                "thumb_800_w": 412,
                "thumb_800_h": 800,
                "thumb_960": "https:\/\/files.slack.com\/files-tmb\/T04HC2CMNJ0-F04LSE53P0F-7385412c1b\/screenshot_2023-01-30_at_11.47.14_am_960.png?t=xoxe-4590080736612-5103277303719-5114876852661-7c6954f20f96cb848404111e9d27c8e9",
                "thumb_960_w": 494,
                "thumb_960_h": 960,
                "thumb_1024": "https:\/\/files.slack.com\/files-tmb\/T04HC2CMNJ0-F04LSE53P0F-7385412c1b\/screenshot_2023-01-30_at_11.47.14_am_1024.png?t=xoxe-4590080736612-5103277303719-5114876852661-7c6954f20f96cb848404111e9d27c8e9",
                "thumb_1024_w": 527,
                "thumb_1024_h": 1024,
                "original_w": 794,
                "original_h": 1542,
                "thumb_tiny": "AwAwABi5cT\/Z9pC7t3vUH9o\/9M\/\/AB6l1LpH9TUGY9mfl3Y3fj0x\/WkMu21x54Y7duD61PVLTfuyfUVdpiK9xD9o2j5htJ7A1F\/Zw\/56n\/vmrZ4POKXgDnigCK3g+zhhu3bj6VNRmigBpz6n8qUH\/OKMUtABRRRQB\/\/Z",
                "permalink": "https:\/\/is-1003-spring-2023.slack.com\/files\/U04LRCJ5LRM\/F04LSE53P0F\/screenshot_2023-01-30_at_11.47.14_am.png",
                "permalink_public": "https:\/\/slack-files.com\/T04HC2CMNJ0-F04LSE53P0F-93df2e198c",
                "is_starred": false,
                "has_rich_preview": false,
                "file_access": "visible"
            }
        ],
        "upload": false,
        "user": "U04LRCJ5LRM",
        "display_as_bot": false,
        "ts": "1675110005.935079",
        "blocks": [
            {
                "type": "rich_text",
                "block_id": "F+3e",
                "elements": [
                    {
                        "type": "rich_text_section",
                        "elements": [
                            {
                                "type": "text",
                                "text": "Hello everyone, this is my profile"
                            }
                        ]
                    }
                ]
            }
        ],
        "client_msg_id": "1409af20-4049-42c5-925e-8a70335f85d8"
    },
    {
        "type": "message",
        "text": "Hello everyone, this is my profile ",
        "files": [
            {
                "id": "F04MX4U819N",
                "created": 1675114844,
                "timestamp": 1675114844,
                "name": "File.jpg",
                "title": "File from iOS (1)",
                "mimetype": "image\/jpeg",
                "filetype": "jpg",
                "pretty_type": "JPEG",
                "user": "U04M0P2DW94",
                "user_team": "T04HC2CMNJ0",
                "editable": false,
                "size": 105794,
                "mode": "hosted",
                "is_external": false,
                "external_type": "",
                "is_public": true,
                "public_url_shared": false,
                "display_as_bot": false,
                "username": "",
                "url_private": "https:\/\/files.slack.com\/files-pri\/T04HC2CMNJ0-F04MX4U819N\/file.jpg?t=xoxe-4590080736612-5103277303719-5114876852661-7c6954f20f96cb848404111e9d27c8e9",
                "url_private_download": "https:\/\/files.slack.com\/files-pri\/T04HC2CMNJ0-F04MX4U819N\/download\/file.jpg?t=xoxe-4590080736612-5103277303719-5114876852661-7c6954f20f96cb848404111e9d27c8e9",
                "media_display_type": "unknown",
                "thumb_64": "https:\/\/files.slack.com\/files-tmb\/T04HC2CMNJ0-F04MX4U819N-62c29d6d94\/file_64.jpg?t=xoxe-4590080736612-5103277303719-5114876852661-7c6954f20f96cb848404111e9d27c8e9",
                "thumb_80": "https:\/\/files.slack.com\/files-tmb\/T04HC2CMNJ0-F04MX4U819N-62c29d6d94\/file_80.jpg?t=xoxe-4590080736612-5103277303719-5114876852661-7c6954f20f96cb848404111e9d27c8e9",
                "thumb_360": "https:\/\/files.slack.com\/files-tmb\/T04HC2CMNJ0-F04MX4U819N-62c29d6d94\/file_360.jpg?t=xoxe-4590080736612-5103277303719-5114876852661-7c6954f20f96cb848404111e9d27c8e9",
                "thumb_360_w": 176,
                "thumb_360_h": 360,
                "thumb_480": "https:\/\/files.slack.com\/files-tmb\/T04HC2CMNJ0-F04MX4U819N-62c29d6d94\/file_480.jpg?t=xoxe-4590080736612-5103277303719-5114876852661-7c6954f20f96cb848404111e9d27c8e9",
                "thumb_480_w": 235,
                "thumb_480_h": 480,
                "thumb_160": "https:\/\/files.slack.com\/files-tmb\/T04HC2CMNJ0-F04MX4U819N-62c29d6d94\/file_160.jpg?t=xoxe-4590080736612-5103277303719-5114876852661-7c6954f20f96cb848404111e9d27c8e9",
                "thumb_720": "https:\/\/files.slack.com\/files-tmb\/T04HC2CMNJ0-F04MX4U819N-62c29d6d94\/file_720.jpg?t=xoxe-4590080736612-5103277303719-5114876852661-7c6954f20f96cb848404111e9d27c8e9",
                "thumb_720_w": 352,
                "thumb_720_h": 720,
                "thumb_800": "https:\/\/files.slack.com\/files-tmb\/T04HC2CMNJ0-F04MX4U819N-62c29d6d94\/file_800.jpg?t=xoxe-4590080736612-5103277303719-5114876852661-7c6954f20f96cb848404111e9d27c8e9",
                "thumb_800_w": 800,
                "thumb_800_h": 1635,
                "thumb_960": "https:\/\/files.slack.com\/files-tmb\/T04HC2CMNJ0-F04MX4U819N-62c29d6d94\/file_960.jpg?t=xoxe-4590080736612-5103277303719-5114876852661-7c6954f20f96cb848404111e9d27c8e9",
                "thumb_960_w": 470,
                "thumb_960_h": 960,
                "thumb_1024": "https:\/\/files.slack.com\/files-tmb\/T04HC2CMNJ0-F04MX4U819N-62c29d6d94\/file_1024.jpg?t=xoxe-4590080736612-5103277303719-5114876852661-7c6954f20f96cb848404111e9d27c8e9",
                "thumb_1024_w": 501,
                "thumb_1024_h": 1024,
                "original_w": 1170,
                "original_h": 2391,
                "thumb_tiny": "AwAwABfRdwiFm6Dmqa3pZ+I8\/Q0++bFuQD3FQxJsT5WGTQBfVwwBHQ07NQx\/LtXPSpaAMu+YmUAZ4zU9umFQ5yMVYMSF9xC59Sop6Rqq4AGPYYoAav3xUlGAO1LQAU0de9OpN6\/3h+dAC0UUUAf\/2Q==",
                "permalink": "https:\/\/is-1003-spring-2023.slack.com\/files\/U04M0P2DW94\/F04MX4U819N\/file.jpg",
                "permalink_public": "https:\/\/slack-files.com\/T04HC2CMNJ0-F04MX4U819N-a3a4da056d",
                "is_starred": false,
                "has_rich_preview": false,
                "file_access": "visible"
            }
        ],
        "upload": false,
        "user": "U04M0P2DW94",
        "display_as_bot": false,
        "ts": "1675114872.285299",
        "blocks": [
            {
                "type": "rich_text",
                "block_id": "UhoR",
                "elements": [
                    {
                        "type": "rich_text_section",
                        "elements": [
                            {
                                "type": "text",
                                "text": "Hello everyone, this is my profile"
                            }
                        ]
                    }
                ]
            }
        ]
    },
    {
        "type": "message",
        "text": "Hi guys! Heres my profile",
        "files": [
            {
                "id": "F04M7ETEWUA",
                "created": 1675115223,
                "timestamp": 1675115223,
                "name": "B78F6542-C566-41AE-BB9D-34DD54523883.jpeg",
                "title": "B78F6542-C566-41AE-BB9D-34DD54523883.jpeg",
                "mimetype": "image\/jpeg",
                "filetype": "jpg",
                "pretty_type": "JPEG",
                "user": "U04LSQ5CQLF",
                "user_team": "T04HC2CMNJ0",
                "editable": false,
                "size": 47023,
                "mode": "hosted",
                "is_external": false,
                "external_type": "",
                "is_public": true,
                "public_url_shared": false,
                "display_as_bot": false,
                "username": "",
                "url_private": "https:\/\/files.slack.com\/files-pri\/T04HC2CMNJ0-F04M7ETEWUA\/b78f6542-c566-41ae-bb9d-34dd54523883.jpeg?t=xoxe-4590080736612-5103277303719-5114876852661-7c6954f20f96cb848404111e9d27c8e9",
                "url_private_download": "https:\/\/files.slack.com\/files-pri\/T04HC2CMNJ0-F04M7ETEWUA\/download\/b78f6542-c566-41ae-bb9d-34dd54523883.jpeg?t=xoxe-4590080736612-5103277303719-5114876852661-7c6954f20f96cb848404111e9d27c8e9",
                "media_display_type": "unknown",
                "thumb_64": "https:\/\/files.slack.com\/files-tmb\/T04HC2CMNJ0-F04M7ETEWUA-fedd879460\/b78f6542-c566-41ae-bb9d-34dd54523883_64.jpg?t=xoxe-4590080736612-5103277303719-5114876852661-7c6954f20f96cb848404111e9d27c8e9",
                "thumb_80": "https:\/\/files.slack.com\/files-tmb\/T04HC2CMNJ0-F04M7ETEWUA-fedd879460\/b78f6542-c566-41ae-bb9d-34dd54523883_80.jpg?t=xoxe-4590080736612-5103277303719-5114876852661-7c6954f20f96cb848404111e9d27c8e9",
                "thumb_360": "https:\/\/files.slack.com\/files-tmb\/T04HC2CMNJ0-F04M7ETEWUA-fedd879460\/b78f6542-c566-41ae-bb9d-34dd54523883_360.jpg?t=xoxe-4590080736612-5103277303719-5114876852661-7c6954f20f96cb848404111e9d27c8e9",
                "thumb_360_w": 248,
                "thumb_360_h": 360,
                "thumb_480": "https:\/\/files.slack.com\/files-tmb\/T04HC2CMNJ0-F04M7ETEWUA-fedd879460\/b78f6542-c566-41ae-bb9d-34dd54523883_480.jpg?t=xoxe-4590080736612-5103277303719-5114876852661-7c6954f20f96cb848404111e9d27c8e9",
                "thumb_480_w": 331,
                "thumb_480_h": 480,
                "thumb_160": "https:\/\/files.slack.com\/files-tmb\/T04HC2CMNJ0-F04M7ETEWUA-fedd879460\/b78f6542-c566-41ae-bb9d-34dd54523883_160.jpg?t=xoxe-4590080736612-5103277303719-5114876852661-7c6954f20f96cb848404111e9d27c8e9",
                "original_w": 372,
                "original_h": 540,
                "thumb_tiny": "AwAwACG\/IVjHmMWwOwNR\/bI\/Rvyp12cW5PuP51msNzg5NIaL5vYgcEP+VSRXCTEqmcgdxWY6qrjHGe1WdP8A9a\/+6KLg0X6KKKYiG7\/49zn1H86pKm47s8elXZtsiGMlh77SajWNFAAZuP8AYNAELQ4BDU+zTZO4\/wBkVP5YkyQx\/EUqReXIz5zkYxigCWikyPf8qMj3\/KgBpHPQ08fXNNI9APxoC+oX8KAHUUhz2x+NHNAC0UUUAf\/Z",
                "permalink": "https:\/\/is-1003-spring-2023.slack.com\/files\/U04LSQ5CQLF\/F04M7ETEWUA\/b78f6542-c566-41ae-bb9d-34dd54523883.jpeg",
                "permalink_public": "https:\/\/slack-files.com\/T04HC2CMNJ0-F04M7ETEWUA-c33f1dfe28",
                "is_starred": false,
                "has_rich_preview": false,
                "file_access": "visible"
            }
        ],
        "upload": false,
        "user": "U04LSQ5CQLF",
        "display_as_bot": false,
        "ts": "1675115238.726869",
        "blocks": [
            {
                "type": "rich_text",
                "block_id": "ND4Yg",
                "elements": [
                    {
                        "type": "rich_text_section",
                        "elements": [
                            {
                                "type": "text",
                                "text": "Hi guys! Heres my profile"
                            }
                        ]
                    }
                ]
            }
        ],
        "client_msg_id": "da5b57da-326f-41f9-831d-daf249684a30"
    },
    {
        "type": "message",
        "text": "Hi this is my Profile.",
        "files": [
            {
                "id": "F04MXJ6TBA4",
                "created": 1675120793,
                "timestamp": 1675120793,
                "name": "slack profile.png",
                "title": "slack profile.png",
                "mimetype": "image\/png",
                "filetype": "png",
                "pretty_type": "PNG",
                "user": "U04M7Q5HXSN",
                "user_team": "T04HC2CMNJ0",
                "editable": false,
                "size": 136697,
                "mode": "hosted",
                "is_external": false,
                "external_type": "",
                "is_public": true,
                "public_url_shared": false,
                "display_as_bot": false,
                "username": "",
                "url_private": "https:\/\/files.slack.com\/files-pri\/T04HC2CMNJ0-F04MXJ6TBA4\/slack_profile.png?t=xoxe-4590080736612-5103277303719-5114876852661-7c6954f20f96cb848404111e9d27c8e9",
                "url_private_download": "https:\/\/files.slack.com\/files-pri\/T04HC2CMNJ0-F04MXJ6TBA4\/download\/slack_profile.png?t=xoxe-4590080736612-5103277303719-5114876852661-7c6954f20f96cb848404111e9d27c8e9",
                "media_display_type": "unknown",
                "thumb_64": "https:\/\/files.slack.com\/files-tmb\/T04HC2CMNJ0-F04MXJ6TBA4-2524b5f007\/slack_profile_64.png?t=xoxe-4590080736612-5103277303719-5114876852661-7c6954f20f96cb848404111e9d27c8e9",
                "thumb_80": "https:\/\/files.slack.com\/files-tmb\/T04HC2CMNJ0-F04MXJ6TBA4-2524b5f007\/slack_profile_80.png?t=xoxe-4590080736612-5103277303719-5114876852661-7c6954f20f96cb848404111e9d27c8e9",
                "thumb_360": "https:\/\/files.slack.com\/files-tmb\/T04HC2CMNJ0-F04MXJ6TBA4-2524b5f007\/slack_profile_360.png?t=xoxe-4590080736612-5103277303719-5114876852661-7c6954f20f96cb848404111e9d27c8e9",
                "thumb_360_w": 309,
                "thumb_360_h": 360,
                "thumb_480": "https:\/\/files.slack.com\/files-tmb\/T04HC2CMNJ0-F04MXJ6TBA4-2524b5f007\/slack_profile_480.png?t=xoxe-4590080736612-5103277303719-5114876852661-7c6954f20f96cb848404111e9d27c8e9",
                "thumb_480_w": 412,
                "thumb_480_h": 480,
                "thumb_160": "https:\/\/files.slack.com\/files-tmb\/T04HC2CMNJ0-F04MXJ6TBA4-2524b5f007\/slack_profile_160.png?t=xoxe-4590080736612-5103277303719-5114876852661-7c6954f20f96cb848404111e9d27c8e9",
                "thumb_720": "https:\/\/files.slack.com\/files-tmb\/T04HC2CMNJ0-F04MXJ6TBA4-2524b5f007\/slack_profile_720.png?t=xoxe-4590080736612-5103277303719-5114876852661-7c6954f20f96cb848404111e9d27c8e9",
                "thumb_720_w": 619,
                "thumb_720_h": 720,
                "thumb_800": "https:\/\/files.slack.com\/files-tmb\/T04HC2CMNJ0-F04MXJ6TBA4-2524b5f007\/slack_profile_800.png?t=xoxe-4590080736612-5103277303719-5114876852661-7c6954f20f96cb848404111e9d27c8e9",
                "thumb_800_w": 687,
                "thumb_800_h": 800,
                "original_w": 696,
                "original_h": 810,
                "thumb_tiny": "AwAwACmkPujgH8KaTk9APpSgcdKTFACU9Iy4YjgKMmm4qxaruEinuBQBEsLuCVxxzzxUea1W+7z1CnFZFAMkBOBgUhPqBS9qTmgAz7ClDEdCRn0pKSgB7SMcfM3HuaZRRQA4dOh\/KkPXvRmigBKKKWgBKKXHHUUlAH\/\/2Q==",
                "permalink": "https:\/\/is-1003-spring-2023.slack.com\/files\/U04M7Q5HXSN\/F04MXJ6TBA4\/slack_profile.png",
                "permalink_public": "https:\/\/slack-files.com\/T04HC2CMNJ0-F04MXJ6TBA4-ccea4d601c",
                "is_starred": false,
                "has_rich_preview": false,
                "file_access": "visible"
            }
        ],
        "upload": false,
        "user": "U04M7Q5HXSN",
        "display_as_bot": false,
        "ts": "1675120841.053029",
        "blocks": [
            {
                "type": "rich_text",
                "block_id": "IDH",
                "elements": [
                    {
                        "type": "rich_text_section",
                        "elements": [
                            {
                                "type": "text",
                                "text": "Hi this is my Profile."
                            }
                        ]
                    }
                ]
            }
        ],
        "client_msg_id": "3b7aa03f-a2df-4797-9310-e9fd3490d855"
    },
    {
        "type": "message",
        "text": "Hey y'all this is my slack profile. I wish everyone good luck this semester!",
        "files": [
            {
                "id": "F04M88NT0Q2",
                "created": 1675127175,
                "timestamp": 1675127175,
                "name": "Tregn Slack Profile screenshot.png",
                "title": "Tregn Slack Profile screenshot.png",
                "mimetype": "image\/png",
                "filetype": "png",
                "pretty_type": "PNG",
                "user": "U04LVMZ0TEW",
                "user_team": "T04HC2CMNJ0",
                "editable": false,
                "size": 28971,
                "mode": "hosted",
                "is_external": false,
                "external_type": "",
                "is_public": true,
                "public_url_shared": false,
                "display_as_bot": false,
                "username": "",
                "url_private": "https:\/\/files.slack.com\/files-pri\/T04HC2CMNJ0-F04M88NT0Q2\/tregn_slack_profile_screenshot.png?t=xoxe-4590080736612-5103277303719-5114876852661-7c6954f20f96cb848404111e9d27c8e9",
                "url_private_download": "https:\/\/files.slack.com\/files-pri\/T04HC2CMNJ0-F04M88NT0Q2\/download\/tregn_slack_profile_screenshot.png?t=xoxe-4590080736612-5103277303719-5114876852661-7c6954f20f96cb848404111e9d27c8e9",
                "media_display_type": "unknown",
                "thumb_64": "https:\/\/files.slack.com\/files-tmb\/T04HC2CMNJ0-F04M88NT0Q2-d31ae2eb9b\/tregn_slack_profile_screenshot_64.png?t=xoxe-4590080736612-5103277303719-5114876852661-7c6954f20f96cb848404111e9d27c8e9",
                "thumb_80": "https:\/\/files.slack.com\/files-tmb\/T04HC2CMNJ0-F04M88NT0Q2-d31ae2eb9b\/tregn_slack_profile_screenshot_80.png?t=xoxe-4590080736612-5103277303719-5114876852661-7c6954f20f96cb848404111e9d27c8e9",
                "thumb_360": "https:\/\/files.slack.com\/files-tmb\/T04HC2CMNJ0-F04M88NT0Q2-d31ae2eb9b\/tregn_slack_profile_screenshot_360.png?t=xoxe-4590080736612-5103277303719-5114876852661-7c6954f20f96cb848404111e9d27c8e9",
                "thumb_360_w": 150,
                "thumb_360_h": 360,
                "thumb_480": "https:\/\/files.slack.com\/files-tmb\/T04HC2CMNJ0-F04M88NT0Q2-d31ae2eb9b\/tregn_slack_profile_screenshot_480.png?t=xoxe-4590080736612-5103277303719-5114876852661-7c6954f20f96cb848404111e9d27c8e9",
                "thumb_480_w": 200,
                "thumb_480_h": 480,
                "thumb_160": "https:\/\/files.slack.com\/files-tmb\/T04HC2CMNJ0-F04M88NT0Q2-d31ae2eb9b\/tregn_slack_profile_screenshot_160.png?t=xoxe-4590080736612-5103277303719-5114876852661-7c6954f20f96cb848404111e9d27c8e9",
                "thumb_720": "https:\/\/files.slack.com\/files-tmb\/T04HC2CMNJ0-F04M88NT0Q2-d31ae2eb9b\/tregn_slack_profile_screenshot_720.png?t=xoxe-4590080736612-5103277303719-5114876852661-7c6954f20f96cb848404111e9d27c8e9",
                "thumb_720_w": 300,
                "thumb_720_h": 720,
                "thumb_800": "https:\/\/files.slack.com\/files-tmb\/T04HC2CMNJ0-F04M88NT0Q2-d31ae2eb9b\/tregn_slack_profile_screenshot_800.png?t=xoxe-4590080736612-5103277303719-5114876852661-7c6954f20f96cb848404111e9d27c8e9",
                "thumb_800_w": 333,
                "thumb_800_h": 800,
                "original_w": 398,
                "original_h": 955,
                "thumb_tiny": "AwAwABSzdXDW7KFUHIzzUJvpV6xqPrmjUvvp9DVRm3Y9hitElYzbdzaU5UH1FLSJ9xfpS1maDcDPP86dgegpueadQAUUUUAGKKKKACiiigD\/2Q==",
                "permalink": "https:\/\/is-1003-spring-2023.slack.com\/files\/U04LVMZ0TEW\/F04M88NT0Q2\/tregn_slack_profile_screenshot.png",
                "permalink_public": "https:\/\/slack-files.com\/T04HC2CMNJ0-F04M88NT0Q2-bbb6a2424c",
                "is_starred": false,
                "has_rich_preview": false,
                "file_access": "visible"
            }
        ],
        "upload": false,
        "user": "U04LVMZ0TEW",
        "display_as_bot": false,
        "ts": "1675127258.574249",
        "blocks": [
            {
                "type": "rich_text",
                "block_id": "7jGYW",
                "elements": [
                    {
                        "type": "rich_text_section",
                        "elements": [
                            {
                                "type": "text",
                                "text": "Hey y'all this is my slack profile. I wish everyone good luck this semester!"
                            }
                        ]
                    }
                ]
            }
        ],
        "client_msg_id": "cc16ac64-a5d0-4b5a-8c6a-6449aadb4897"
    },
    {
        "type": "message",
        "text": "Hello everyone. Have a great semester!",
        "files": [
            {
                "id": "F04M24M54MC",
                "created": 1675136900,
                "timestamp": 1675136900,
                "name": "image.png",
                "title": "image.png",
                "mimetype": "image\/png",
                "filetype": "png",
                "pretty_type": "PNG",
                "user": "U04LU4G6VDM",
                "user_team": "T04HC2CMNJ0",
                "editable": false,
                "size": 278407,
                "mode": "hosted",
                "is_external": false,
                "external_type": "",
                "is_public": true,
                "public_url_shared": false,
                "display_as_bot": false,
                "username": "",
                "url_private": "https:\/\/files.slack.com\/files-pri\/T04HC2CMNJ0-F04M24M54MC\/image.png?t=xoxe-4590080736612-5103277303719-5114876852661-7c6954f20f96cb848404111e9d27c8e9",
                "url_private_download": "https:\/\/files.slack.com\/files-pri\/T04HC2CMNJ0-F04M24M54MC\/download\/image.png?t=xoxe-4590080736612-5103277303719-5114876852661-7c6954f20f96cb848404111e9d27c8e9",
                "media_display_type": "unknown",
                "thumb_64": "https:\/\/files.slack.com\/files-tmb\/T04HC2CMNJ0-F04M24M54MC-cb19297c0b\/image_64.png?t=xoxe-4590080736612-5103277303719-5114876852661-7c6954f20f96cb848404111e9d27c8e9",
                "thumb_80": "https:\/\/files.slack.com\/files-tmb\/T04HC2CMNJ0-F04M24M54MC-cb19297c0b\/image_80.png?t=xoxe-4590080736612-5103277303719-5114876852661-7c6954f20f96cb848404111e9d27c8e9",
                "thumb_360": "https:\/\/files.slack.com\/files-tmb\/T04HC2CMNJ0-F04M24M54MC-cb19297c0b\/image_360.png?t=xoxe-4590080736612-5103277303719-5114876852661-7c6954f20f96cb848404111e9d27c8e9",
                "thumb_360_w": 153,
                "thumb_360_h": 360,
                "thumb_480": "https:\/\/files.slack.com\/files-tmb\/T04HC2CMNJ0-F04M24M54MC-cb19297c0b\/image_480.png?t=xoxe-4590080736612-5103277303719-5114876852661-7c6954f20f96cb848404111e9d27c8e9",
                "thumb_480_w": 204,
                "thumb_480_h": 480,
                "thumb_160": "https:\/\/files.slack.com\/files-tmb\/T04HC2CMNJ0-F04M24M54MC-cb19297c0b\/image_160.png?t=xoxe-4590080736612-5103277303719-5114876852661-7c6954f20f96cb848404111e9d27c8e9",
                "thumb_720": "https:\/\/files.slack.com\/files-tmb\/T04HC2CMNJ0-F04M24M54MC-cb19297c0b\/image_720.png?t=xoxe-4590080736612-5103277303719-5114876852661-7c6954f20f96cb848404111e9d27c8e9",
                "thumb_720_w": 305,
                "thumb_720_h": 720,
                "thumb_800": "https:\/\/files.slack.com\/files-tmb\/T04HC2CMNJ0-F04M24M54MC-cb19297c0b\/image_800.png?t=xoxe-4590080736612-5103277303719-5114876852661-7c6954f20f96cb848404111e9d27c8e9",
                "thumb_800_w": 339,
                "thumb_800_h": 800,
                "thumb_960": "https:\/\/files.slack.com\/files-tmb\/T04HC2CMNJ0-F04M24M54MC-cb19297c0b\/image_960.png?t=xoxe-4590080736612-5103277303719-5114876852661-7c6954f20f96cb848404111e9d27c8e9",
                "thumb_960_w": 407,
                "thumb_960_h": 960,
                "thumb_1024": "https:\/\/files.slack.com\/files-tmb\/T04HC2CMNJ0-F04M24M54MC-cb19297c0b\/image_1024.png?t=xoxe-4590080736612-5103277303719-5114876852661-7c6954f20f96cb848404111e9d27c8e9",
                "thumb_1024_w": 434,
                "thumb_1024_h": 1024,
                "original_w": 456,
                "original_h": 1075,
                "thumb_tiny": "AwAwABSEWxkVMNlmXOMdKSC2EpZS5Vh2xVmLiOI4z8gxUO\/yrklecHmlcdiC4j8mUpnOO9RZqe+Ia5JHQgfyqCmItByfLBBwg7YqOaQNPvXK8Uzt2pp\/CiwXHSHe2fbvTcUUUAPxxjP6U3PbNGfrRzQAlFFFAH\/\/2Q==",
                "permalink": "https:\/\/is-1003-spring-2023.slack.com\/files\/U04LU4G6VDM\/F04M24M54MC\/image.png",
                "permalink_public": "https:\/\/slack-files.com\/T04HC2CMNJ0-F04M24M54MC-97b36fb08d",
                "is_starred": false,
                "has_rich_preview": false,
                "file_access": "visible"
            }
        ],
        "upload": false,
        "user": "U04LU4G6VDM",
        "display_as_bot": false,
        "ts": "1675136924.538849",
        "blocks": [
            {
                "type": "rich_text",
                "block_id": "fZHC",
                "elements": [
                    {
                        "type": "rich_text_section",
                        "elements": [
                            {
                                "type": "text",
                                "text": "Hello everyone. Have a great semester!"
                            }
                        ]
                    }
                ]
            }
        ],
        "client_msg_id": "f23ebcec-5c94-4391-86b3-562862a19979"
    },
    {
        "client_msg_id": "3ea2c6eb-4459-4437-9ecf-1705d929a0d3",
        "type": "message",
        "text": "Is there a specific word count that we have to go by for each breakout ?",
        "user": "U04LRCJ5LRM",
        "ts": "1675138458.411089",
        "blocks": [
            {
                "type": "rich_text",
                "block_id": "fDdA",
                "elements": [
                    {
                        "type": "rich_text_section",
                        "elements": [
                            {
                                "type": "text",
                                "text": "Is there a specific word count that we have to go by for each breakout ?"
                            }
                        ]
                    }
                ]
            }
        ],
        "team": "T04HC2CMNJ0",
        "user_team": "T04HC2CMNJ0",
        "source_team": "T04HC2CMNJ0",
        "user_profile": {
            "avatar_hash": "25d6837b2551",
            "image_72": "https:\/\/avatars.slack-edge.com\/2023-01-31\/4753644485664_25d6837b255182d3d37b_72.jpg",
            "first_name": "Will",
            "real_name": "Will Adams",
            "display_name": "Will Adams",
            "team": "T04HC2CMNJ0",
            "name": "willjusttinadams",
            "is_restricted": false,
            "is_ultra_restricted": false
        },
        "thread_ts": "1675138458.411089",
        "reply_count": 1,
        "reply_users_count": 1,
        "latest_reply": "1675169261.017569",
        "reply_users": [
            "U04KKRC0ZRA"
        ],
        "replies": [
            {
                "user": "U04KKRC0ZRA",
                "ts": "1675169261.017569"
            }
        ],
        "is_locked": false,
        "subscribed": false
    },
    {
        "client_msg_id": "dd997697-40bf-43ef-8072-24c3ddacccd3",
        "type": "message",
        "text": "I second that question also do we have to make a special title or did yall just title it reporting?",
        "user": "U04M5GNEYN5",
        "ts": "1675141335.667179",
        "blocks": [
            {
                "type": "rich_text",
                "block_id": "6qlO",
                "elements": [
                    {
                        "type": "rich_text_section",
                        "elements": [
                            {
                                "type": "text",
                                "text": "I second that question also do we have to make a special title or did yall just title it reporting?"
                            }
                        ]
                    }
                ]
            }
        ],
        "team": "T04HC2CMNJ0",
        "user_team": "T04HC2CMNJ0",
        "source_team": "T04HC2CMNJ0",
        "user_profile": {
            "avatar_hash": "2383cd945f3f",
            "image_72": "https:\/\/avatars.slack-edge.com\/2023-01-26\/4700350048646_2383cd945f3ff798d2c9_72.jpg",
            "first_name": "Allysa",
            "real_name": "Allysa Monte De Ramos",
            "display_name": "Allysa Monte De Ramos",
            "team": "T04HC2CMNJ0",
            "name": "allysa.montederamos",
            "is_restricted": false,
            "is_ultra_restricted": false
        },
        "thread_ts": "1675141335.667179",
        "reply_count": 1,
        "reply_users_count": 1,
        "latest_reply": "1675170860.037879",
        "reply_users": [
            "U04KKRC0ZRA"
        ],
        "replies": [
            {
                "user": "U04KKRC0ZRA",
                "ts": "1675170860.037879"
            }
        ],
        "is_locked": false,
        "subscribed": false
    },
    {
        "client_msg_id": "226036a9-bca5-49b2-a3b6-b4c97d004888",
        "type": "message",
        "text": "How long were yall's introductions?",
        "user": "U04M5GNEYN5",
        "ts": "1675142637.912749",
        "blocks": [
            {
                "type": "rich_text",
                "block_id": "rqL2v",
                "elements": [
                    {
                        "type": "rich_text_section",
                        "elements": [
                            {
                                "type": "text",
                                "text": "How long were yall's introductions?"
                            }
                        ]
                    }
                ]
            }
        ],
        "team": "T04HC2CMNJ0",
        "user_team": "T04HC2CMNJ0",
        "source_team": "T04HC2CMNJ0",
        "user_profile": {
            "avatar_hash": "2383cd945f3f",
            "image_72": "https:\/\/avatars.slack-edge.com\/2023-01-26\/4700350048646_2383cd945f3ff798d2c9_72.jpg",
            "first_name": "Allysa",
            "real_name": "Allysa Monte De Ramos",
            "display_name": "Allysa Monte De Ramos",
            "team": "T04HC2CMNJ0",
            "name": "allysa.montederamos",
            "is_restricted": false,
            "is_ultra_restricted": false
        },
        "thread_ts": "1675142637.912749",
        "reply_count": 1,
        "reply_users_count": 1,
        "latest_reply": "1675170102.499459",
        "reply_users": [
            "U04ME79DU2C"
        ],
        "replies": [
            {
                "user": "U04ME79DU2C",
                "ts": "1675170102.499459"
            }
        ],
        "is_locked": false,
        "subscribed": false
    },
    {
        "type": "message",
        "text": "Hi, this is my profile ",
        "files": [
            {
                "id": "F04MYMCH65N",
                "created": 1675143103,
                "timestamp": 1675143103,
                "name": "IMG_2067.png",
                "title": "IMG_2067",
                "mimetype": "image\/png",
                "filetype": "png",
                "pretty_type": "PNG",
                "user": "U04LTD4BGH0",
                "user_team": "T04HC2CMNJ0",
                "editable": false,
                "size": 6432116,
                "mode": "hosted",
                "is_external": false,
                "external_type": "",
                "is_public": true,
                "public_url_shared": false,
                "display_as_bot": false,
                "username": "",
                "url_private": "https:\/\/files.slack.com\/files-pri\/T04HC2CMNJ0-F04MYMCH65N\/img_2067.png?t=xoxe-4590080736612-5103277303719-5114876852661-7c6954f20f96cb848404111e9d27c8e9",
                "url_private_download": "https:\/\/files.slack.com\/files-pri\/T04HC2CMNJ0-F04MYMCH65N\/download\/img_2067.png?t=xoxe-4590080736612-5103277303719-5114876852661-7c6954f20f96cb848404111e9d27c8e9",
                "media_display_type": "unknown",
                "thumb_64": "https:\/\/files.slack.com\/files-tmb\/T04HC2CMNJ0-F04MYMCH65N-be53496571\/img_2067_64.png?t=xoxe-4590080736612-5103277303719-5114876852661-7c6954f20f96cb848404111e9d27c8e9",
                "thumb_80": "https:\/\/files.slack.com\/files-tmb\/T04HC2CMNJ0-F04MYMCH65N-be53496571\/img_2067_80.png?t=xoxe-4590080736612-5103277303719-5114876852661-7c6954f20f96cb848404111e9d27c8e9",
                "thumb_360": "https:\/\/files.slack.com\/files-tmb\/T04HC2CMNJ0-F04MYMCH65N-be53496571\/img_2067_360.png?t=xoxe-4590080736612-5103277303719-5114876852661-7c6954f20f96cb848404111e9d27c8e9",
                "thumb_360_w": 166,
                "thumb_360_h": 360,
                "thumb_480": "https:\/\/files.slack.com\/files-tmb\/T04HC2CMNJ0-F04MYMCH65N-be53496571\/img_2067_480.png?t=xoxe-4590080736612-5103277303719-5114876852661-7c6954f20f96cb848404111e9d27c8e9",
                "thumb_480_w": 221,
                "thumb_480_h": 480,
                "thumb_160": "https:\/\/files.slack.com\/files-tmb\/T04HC2CMNJ0-F04MYMCH65N-be53496571\/img_2067_160.png?t=xoxe-4590080736612-5103277303719-5114876852661-7c6954f20f96cb848404111e9d27c8e9",
                "thumb_720": "https:\/\/files.slack.com\/files-tmb\/T04HC2CMNJ0-F04MYMCH65N-be53496571\/img_2067_720.png?t=xoxe-4590080736612-5103277303719-5114876852661-7c6954f20f96cb848404111e9d27c8e9",
                "thumb_720_w": 332,
                "thumb_720_h": 720,
                "thumb_800": "https:\/\/files.slack.com\/files-tmb\/T04HC2CMNJ0-F04MYMCH65N-be53496571\/img_2067_800.png?t=xoxe-4590080736612-5103277303719-5114876852661-7c6954f20f96cb848404111e9d27c8e9",
                "thumb_800_w": 800,
                "thumb_800_h": 1734,
                "thumb_960": "https:\/\/files.slack.com\/files-tmb\/T04HC2CMNJ0-F04MYMCH65N-be53496571\/img_2067_960.png?t=xoxe-4590080736612-5103277303719-5114876852661-7c6954f20f96cb848404111e9d27c8e9",
                "thumb_960_w": 443,
                "thumb_960_h": 960,
                "thumb_1024": "https:\/\/files.slack.com\/files-tmb\/T04HC2CMNJ0-F04MYMCH65N-be53496571\/img_2067_1024.png?t=xoxe-4590080736612-5103277303719-5114876852661-7c6954f20f96cb848404111e9d27c8e9",
                "thumb_1024_w": 472,
                "thumb_1024_h": 1024,
                "image_exif_rotation": 1,
                "original_w": 1179,
                "original_h": 2556,
                "thumb_tiny": "AwAwABaqIJGUEAEH3oEDlQQP1p0W4EAcZqaN8YU44p6CKzxOoywH4UzafSrtxygx61XxQ7dBjY5HB4xjpyKkWMvIwB57fnUK4HIz69aXewJIODSAnmUeXGcEHGCfU1Dj60m9mwCxIFFADKU9O1Ax\/kUFW9DQAL1p1NBxS5FAH\/\/Z",
                "permalink": "https:\/\/is-1003-spring-2023.slack.com\/files\/U04LTD4BGH0\/F04MYMCH65N\/img_2067.png",
                "permalink_public": "https:\/\/slack-files.com\/T04HC2CMNJ0-F04MYMCH65N-b7aafa384b",
                "is_starred": false,
                "has_rich_preview": false,
                "file_access": "visible"
            }
        ],
        "upload": false,
        "user": "U04LTD4BGH0",
        "display_as_bot": false,
        "ts": "1675143110.419809",
        "blocks": [
            {
                "type": "rich_text",
                "block_id": "zGSl",
                "elements": [
                    {
                        "type": "rich_text_section",
                        "elements": [
                            {
                                "type": "text",
                                "text": "Hi, this is my profile "
                            }
                        ]
                    }
                ]
            }
        ],
        "client_msg_id": "0C947211-50F5-49F0-A3AB-96FEBB888DF2"
    }
]